tbmain.py
tb/__init__.py
tb/bootstrap.py
tb/config.py
tb/first_time.py
tb/job_execution.py
tb/main.py
tb/tb.py
tb/term.py
tb/version.py
tb/arguments/__init__.py
tb/arguments/environment.py
tb/arguments/repository.py
tb/arguments/team.py
tb/arguments/user.py
tb/arguments/validators.py
tb/controllers/__init__.py
tb/controllers/base.py
tb/core/__init__.py
tb/core/exc.py
tb/core/version.py
tb/ext/__init__.py
tb/ext/ext_configobj.py
tb/ext/ext_versionedplugins.py
tb/ext/ext_yaml_configobj2.py
tb/plugins/__init__.py
tb_cli-2.0.18.data/data/tb/plugins/devloop/__init__.py
tb_cli-2.0.18.data/data/tb/plugins/devloop/cmd_devloop.py
tb_cli-2.0.18.data/data/tb/plugins/devloop/test_util.py
tb_cli-2.0.18.data/data/tb/plugins/devloop/util.py
tb_cli-2.0.18.data/data/tb/plugins/repo/__init__.py
tb_cli-2.0.18.data/data/tb/plugins/repo/cmd_repo.py
tb_cli-2.0.18.data/data/tb/plugins.d/devloop.yml
tb_cli-2.0.18.data/data/tb/plugins.d/repo.yml
tb_cli-2.0.18.dist-info/LICENSE.txt
tb_cli-2.0.18.dist-info/METADATA
tb_cli-2.0.18.dist-info/WHEEL
tb_cli-2.0.18.dist-info/entry_points.txt
tb_cli-2.0.18.dist-info/top_level.txt
tb_cli-2.0.18.dist-info/RECORD
