Metadata-Version: 2.1
Name: tb-cli
Version: 2.0.18
Summary: The team b cli
Home-page: https://bitbucket.org/mrdon/tb
Author: Don Brown
Author-email: mrdon@twdata.org
License: aplv2
Platform: UNKNOWN
Classifier: Development Status :: 5 - Production/Stable
Classifier: Intended Audience :: Developers
Classifier: Intended Audience :: System Administrators
Classifier: License :: OSI Approved :: MIT License
Classifier: Operating System :: OS Independent
Classifier: Topic :: Software Development :: Build Tools
Classifier: Topic :: Software Development :: Libraries :: Python Modules
Classifier: Topic :: Internet
Classifier: Programming Language :: Python :: 3
Classifier: Programming Language :: Python :: 3.7
Classifier: Programming Language :: Python :: 3 :: Only
Requires-Python: >=3.7
Requires-Dist: cement (==3.0.2)
Requires-Dist: jinja2 (==2.10)
Requires-Dist: pyyaml (==3.13)
Requires-Dist: colorlog (==4.0.2)
Requires-Dist: prompt-toolkit (==2.0.8)
Requires-Dist: configobj (==5.0.6)
Requires-Dist: requests (==2.21.0)
Requires-Dist: requests-toolbelt (==0.8.0)
Requires-Dist: watchdog (==0.9.0)
Requires-Dist: python-dateutil (==2.7.5)
Requires-Dist: blessings (==1.7)
Requires-Dist: keyring (==11.1.0)
Requires-Dist: tabulate (==0.8.3)
Requires-Dist: ruamel.yaml (==0.15.87)
Requires-Dist: requests-oauthlib (==1.2.0)
Requires-Dist: git-url-parse (==1.2.0)
Requires-Dist: semver (==2.8.1)
